anyregistration
onitool
xndec
