Metadata-Version: 1.0
Name: pyoni
Version: 0.6.1
Summary: Python OpenNI ONI tool
Home-page: https://github.com/eruffaldi/pyoni
Author: Emanuele Ruffaldi
Author-email: emanuele ruffaldi
License: UNKNOWN
Keywords: rgbd,tool,oni,openni
Platform: UNKNOWN
